conservation/__init__.py
conservation/commands.py
conservation/conservation_codon.py
conservation/version.py
conservation/lib/N34_modifications.tsv
conservation-1.0.1.data/scripts/conservation
conservation-1.0.1.dist-info/LICENSE.txt
conservation-1.0.1.dist-info/METADATA
conservation-1.0.1.dist-info/WHEEL
conservation-1.0.1.dist-info/top_level.txt
conservation-1.0.1.dist-info/RECORD
