Metadata-Version: 2.1
Name: conservation
Version: 1.0.1
Summary: Evolutionary Conservation of Amino Acids and Codons
Home-page: https://github.com/hanjunlee21/conservation
Download-URL: https://github.com/hanjunlee21/conservation/archive/refs/tags/v.1.0.1.tar.gz
Author: Hanjun Lee
Author-email: hanjun_lee@hms.harvard.edu
License: MIT
Keywords: bioinformatics
Classifier: Development Status :: 4 - Beta
Classifier: Intended Audience :: Science/Research
Classifier: Topic :: Scientific/Engineering :: Bio-Informatics
Classifier: License :: OSI Approved :: MIT License
Classifier: Programming Language :: Python :: 3
Requires-Python: >=3.6
License-File: LICENSE.txt
Requires-Dist: numpy
Requires-Dist: pandas
Requires-Dist: biopython
Requires-Dist: scipy
Requires-Dist: matplotlib
Requires-Dist: tqdm
Requires-Dist: importlib-resources
